django_context_request/__init__.py
django_context_request/__version__.py
django_context_request/exceptions.py
django_context_request/globals.py
django_context_request/middleware.py
django_context_request/request_context.py
django_context_request-0.1.0.dist-info/LICENSE
django_context_request-0.1.0.dist-info/METADATA
django_context_request-0.1.0.dist-info/WHEEL
django_context_request-0.1.0.dist-info/top_level.txt
django_context_request-0.1.0.dist-info/RECORD
